contaix/__init__.py
contaix/aggregation.py
contaix/code.py
contaix/markdown.py
contaix/urls.py
contaix/util.py
contaix-0.0.11.dist-info/LICENSE
contaix-0.0.11.dist-info/METADATA
contaix-0.0.11.dist-info/WHEEL
contaix-0.0.11.dist-info/top_level.txt
contaix-0.0.11.dist-info/RECORD
