Metadata-Version: 2.1
Name: contaix
Version: 0.0.11
Summary: Tools to make contexts for AI
Home-page: https://github.com/thorwhalen/contaix
Author: Thor Whalen
License: mit
Platform: any
License-File: LICENSE
Requires-Dist: dol
Requires-Dist: dn
Requires-Dist: lkj
Requires-Dist: scraped
Requires-Dist: aix
Requires-Dist: pypdf
Requires-Dist: mammoth
Requires-Dist: pandas
Requires-Dist: python-pptx
Requires-Dist: html2text
Requires-Dist: nbconvert
Requires-Dist: nbformat
Requires-Dist: openpyxl
Requires-Dist: tabulate
Requires-Dist: hubcap
